lbp/__init__.py
lbp-0.1.2.dist-info/METADATA
lbp-0.1.2.dist-info/WHEEL
lbp-0.1.2.dist-info/entry_points.txt
lbp-0.1.2.dist-info/RECORD
