Metadata-Version: 2.4
Name: lbp
Version: 0.1.2
Summary: Shortcuts for LangBot Plugin CLI
Requires-Python: >=3.12
Requires-Dist: langbot-plugin==0.1.1b1
